{
 "actions": [],
 "autoname": "autoincrement",
 "creation": "2022-12-12 13:52:09.254426",
 "doctype": "DocType",
 "editable_grid": 1,
 "engine": "InnoDB",
 "field_order": [
  "name1",
  "wtunit",
  "ts"
 ],
 "fields": [
  {
   "fieldname": "name1",
   "fieldtype": "Data",
   "label": "Name"
  },
  {
   "fieldname": "wtunit",
   "fieldtype": "Float",
   "label": "Wt/Unit"
  },
  {
   "fieldname": "ts",
   "fieldtype": "Button",
   "in_list_view": 1,
   "label": "TS"
  }
 ],
 "index_web_pages_for_search": 1,
 "istable": 1,
 "links": [],
 "modified": "2026-02-26 11:16:12.912113",
 "modified_by": "Administrator",
 "module": "QPIC",
 "name": "Technical Sheet Data Others",
 "naming_rule": "Autoincrement",
 "owner": "Administrator",
 "permissions": [],
 "sort_field": "modified",
 "sort_order": "DESC",
 "states": []
}